<ExportFile>
  <StructuredView Guid="{d9b2b2cc-ea99-4c3b-aa42-1e5c49e65b84}">
<Single xml:space="preserve" Type="{3daac5e4-660e-42e4-9cea-3711b98bfb63}" Method="IArchivable">
  <Null Name="Profile" />
  <List2 Name="EntryList">
    <Single Type="{6198ad31-4b98-445c-927f-3258a0e82fe3}" Method="IArchivable">
      <Single Name="IsRoot" Type="bool">True</Single>
      <Single Name="MetaObject" Type="{81297157-7ec9-45ce-845e-84cab2b88ade}" Method="IArchivable">
        <Single Name="Guid" Type="System.Guid">d6de4a7a-def3-4126-9e84-aa4a70bed0bf</Single>
        <Single Name="ParentGuid" Type="System.Guid">9b280665-8d53-4807-82ac-923441df304e</Single>
        <Single Name="Name" Type="string">RCTU</Single>
        <Dictionary Type="{2c41fa04-1834-41c1-816e-303c7aa2c05b}" Name="Properties" />
        <Single Name="TypeGuid" Type="System.Guid">6f9dac99-8de1-4efc-8465-68ac443b7d08</Single>
        <Array Name="EmbeddedTypeGuids" Type="System.Guid">
          <Single Type="System.Guid">a9ed5b7e-75c5-4651-af16-d2c27e98cb94</Single>
          <Single Type="System.Guid">25e509de-33d4-4447-93f8-c9e4ea381c8b</Single>
        </Array>
        <Single Name="Timestamp" Type="long">0</Single>
      </Single>
      <Single Name="Object" Type="{6f9dac99-8de1-4efc-8465-68ac443b7d08}" Method="IArchivable">
        <Single Name="SpecialFunc" Type="{0db3d7bb-cde0-4416-9a7b-ce49a0124323}">None</Single>
        <Single Name="Implementation" Type="{25e509de-33d4-4447-93f8-c9e4ea381c8b}" Method="IArchivable">
          <Single Name="NetworkListComment" Type="string"></Single>
          <Single Name="DefaultViewMode" Type="string">Ld</Single>
          <List2 Name="NetworkList">
            <Single Type="{d9a99d73-b633-47db-b876-a752acb25871}" Method="IArchivable">
              <Single Name="ILActive" Type="bool">False</Single>
              <Single Name="FBDValid" Type="bool">False</Single>
              <Single Name="ILValid" Type="bool">False</Single>
              <List2 Name="ILLines" />
              <Single Name="Comment" Type="string"></Single>
              <Single Name="Title" Type="string"></Single>
              <Single Name="Label" Type="string"></Single>
              <Single Name="OutCommented" Type="bool">False</Single>
              <List2 Name="NetworkItems">
                <Single Type="{acfc6f68-8e3a-4af5-bf81-3dd512095a46}" Method="IArchivable">
                  <Single Name="BoxType" Type="string">MOVE</Single>
                  <Single Name="Instance" Type="{c9b2f165-48a2-4a45-8326-3952d8a3d708}" Method="IArchivable">
                    <Null Name="Operand" />
                    <Single Name="Type" Type="string"></Single>
                    <Single Name="Comment" Type="string"></Single>
                    <Single Name="SymbolComment" Type="string"></Single>
                    <Single Name="Address" Type="string"></Single>
                    <Single Name="Flags" Type="{668066f2-6069-46b3-8962-8db8d13d7db2}" Method="IArchivable">
                      <Single Name="Flags" Type="int">0</Single>
                      <Single Name="Fixed" Type="bool">False</Single>
                      <Single Name="Extensible" Type="bool">False</Single>
                    </Single>
                    <Single Name="LValue" Type="bool">False</Single>
                    <Single Name="Boolean" Type="bool">False</Single>
                    <Single Name="IsInstance" Type="bool">True</Single>
                    <Single Name="Id" Type="long">31</Single>
                  </Single>
                  <Single Name="OutputItems" Type="{f40d3e09-c02c-4522-a88c-dac23558cfc4}" Method="IArchivable">
                    <List2 Name="OutputItems">
                      <Null />
                      <Single Type="{c9b2f165-48a2-4a45-8326-3952d8a3d708}" Method="IArchivable">
                        <Single Name="Operand" Type="string">CV</Single>
                        <Single Name="Type" Type="string">WORD</Single>
                        <Single Name="Comment" Type="string"></Single>
                        <Single Name="SymbolComment" Type="string"></Single>
                        <Single Name="Address" Type="string"></Single>
                        <Single Name="Flags" Type="{668066f2-6069-46b3-8962-8db8d13d7db2}" Method="IArchivable">
                          <Single Name="Flags" Type="int">0</Single>
                          <Single Name="Fixed" Type="bool">False</Single>
                          <Single Name="Extensible" Type="bool">False</Single>
                        </Single>
                        <Single Name="LValue" Type="bool">True</Single>
                        <Single Name="Boolean" Type="bool">False</Single>
                        <Single Name="IsInstance" Type="bool">False</Single>
                        <Single Name="Id" Type="long">33</Single>
                      </Single>
                    </List2>
                  </Single>
                  <Single Name="Flags" Type="{668066f2-6069-46b3-8962-8db8d13d7db2}" Method="IArchivable">
                    <Single Name="Flags" Type="int">0</Single>
                    <Single Name="Fixed" Type="bool">False</Single>
                    <Single Name="Extensible" Type="bool">False</Single>
                  </Single>
                  <Null Name="InputFlags" />
                  <List2 Name="InputItems">
                    <Single Type="{9de7f100-1b87-424c-a62e-45b0cfc85ed2}" Method="IArchivable">
                      <Single Name="Operand" Type="{c9b2f165-48a2-4a45-8326-3952d8a3d708}" Method="IArchivable">
                        <Single Name="Operand" Type="string">RESET</Single>
                        <Single Name="Type" Type="string">BOOL</Single>
                        <Single Name="Comment" Type="string"></Single>
                        <Single Name="SymbolComment" Type="string"></Single>
                        <Single Name="Address" Type="string"></Single>
                        <Single Name="Flags" Type="{668066f2-6069-46b3-8962-8db8d13d7db2}" Method="IArchivable">
                          <Single Name="Flags" Type="int">0</Single>
                          <Single Name="Fixed" Type="bool">True</Single>
                          <Single Name="Extensible" Type="bool">False</Single>
                        </Single>
                        <Single Name="LValue" Type="bool">False</Single>
                        <Single Name="Boolean" Type="bool">True</Single>
                        <Single Name="IsInstance" Type="bool">False</Single>
                        <Single Name="Id" Type="long">26</Single>
                      </Single>
                      <Single Name="Id" Type="long">25</Single>
                    </Single>
                    <Single Type="{9de7f100-1b87-424c-a62e-45b0cfc85ed2}" Method="IArchivable">
                      <Single Name="Operand" Type="{c9b2f165-48a2-4a45-8326-3952d8a3d708}" Method="IArchivable">
                        <Single Name="Operand" Type="string">RV</Single>
                        <Single Name="Type" Type="string">WORD</Single>
                        <Single Name="Comment" Type="string"></Single>
                        <Single Name="SymbolComment" Type="string"></Single>
                        <Single Name="Address" Type="string"></Single>
                        <Single Name="Flags" Type="{668066f2-6069-46b3-8962-8db8d13d7db2}" Method="IArchivable">
                          <Single Name="Flags" Type="int">0</Single>
                          <Single Name="Fixed" Type="bool">False</Single>
                          <Single Name="Extensible" Type="bool">False</Single>
                        </Single>
                        <Single Name="LValue" Type="bool">False</Single>
                        <Single Name="Boolean" Type="bool">False</Single>
                        <Single Name="IsInstance" Type="bool">False</Single>
                        <Single Name="Id" Type="long">35</Single>
                      </Single>
                      <Single Name="Id" Type="long">34</Single>
                    </Single>
                  </List2>
                  <Single Name="InputParam" Type="{71496971-9e0c-4677-a832-b9583b571130}" Method="IArchivable">
                    <List2 Name="Names">
                      <Single Type="string">EN</Single>
                    </List2>
                    <List2 Name="Types">
                      <Single Type="string">BOOL</Single>
                    </List2>
                  </Single>
                  <Single Name="OutputParam" Type="{71496971-9e0c-4677-a832-b9583b571130}" Method="IArchivable">
                    <List2 Name="Names">
                      <Single Type="string">ENO</Single>
                      <Single Type="string"></Single>
                    </List2>
                    <List2 Name="Types">
                      <Single Type="string">BOOL</Single>
                      <Single Type="string"></Single>
                    </List2>
                  </Single>
                  <Single Name="CallType" Type="{bffb3c53-f105-4e85-aba2-e30df579d75f}">Move</Single>
                  <Single Name="EN" Type="bool">True</Single>
                  <Single Name="ENO" Type="bool">True</Single>
                  <Null Name="STSnippet" />
                  <Single Name="ContainsExtensibleInputs" Type="bool">False</Single>
                  <Single Name="ProvidesSTSnippet" Type="bool">False</Single>
                  <Single Name="Id" Type="long">32</Single>
                </Single>
              </List2>
              <List2 Name="Connectors" />
              <Single Name="Id" Type="long">24</Single>
            </Single>
            <Single Type="{d9a99d73-b633-47db-b876-a752acb25871}" Method="IArchivable">
              <Single Name="ILActive" Type="bool">False</Single>
              <Single Name="FBDValid" Type="bool">False</Single>
              <Single Name="ILValid" Type="bool">False</Single>
              <List2 Name="ILLines" />
              <Single Name="Comment" Type="string"></Single>
              <Single Name="Title" Type="string"></Single>
              <Single Name="Label" Type="string"></Single>
              <Single Name="OutCommented" Type="bool">False</Single>
              <List2 Name="NetworkItems">
                <Single Type="{acfc6f68-8e3a-4af5-bf81-3dd512095a46}" Method="IArchivable">
                  <Single Name="BoxType" Type="string">MOVE</Single>
                  <Single Name="Instance" Type="{c9b2f165-48a2-4a45-8326-3952d8a3d708}" Method="IArchivable">
                    <Null Name="Operand" />
                    <Single Name="Type" Type="string"></Single>
                    <Single Name="Comment" Type="string"></Single>
                    <Single Name="SymbolComment" Type="string"></Single>
                    <Single Name="Address" Type="string"></Single>
                    <Single Name="Flags" Type="{668066f2-6069-46b3-8962-8db8d13d7db2}" Method="IArchivable">
                      <Single Name="Flags" Type="int">0</Single>
                      <Single Name="Fixed" Type="bool">False</Single>
                      <Single Name="Extensible" Type="bool">False</Single>
                    </Single>
                    <Single Name="LValue" Type="bool">False</Single>
                    <Single Name="Boolean" Type="bool">False</Single>
                    <Single Name="IsInstance" Type="bool">True</Single>
                    <Single Name="Id" Type="long">77</Single>
                  </Single>
                  <Single Name="OutputItems" Type="{f40d3e09-c02c-4522-a88c-dac23558cfc4}" Method="IArchivable">
                    <List2 Name="OutputItems">
                      <Null />
                      <Single Type="{c9b2f165-48a2-4a45-8326-3952d8a3d708}" Method="IArchivable">
                        <Single Name="Operand" Type="string">CV</Single>
                        <Single Name="Type" Type="string">WORD</Single>
                        <Single Name="Comment" Type="string"></Single>
                        <Single Name="SymbolComment" Type="string"></Single>
                        <Single Name="Address" Type="string"></Single>
                        <Single Name="Flags" Type="{668066f2-6069-46b3-8962-8db8d13d7db2}" Method="IArchivable">
                          <Single Name="Flags" Type="int">0</Single>
                          <Single Name="Fixed" Type="bool">False</Single>
                          <Single Name="Extensible" Type="bool">False</Single>
                        </Single>
                        <Single Name="LValue" Type="bool">True</Single>
                        <Single Name="Boolean" Type="bool">False</Single>
                        <Single Name="IsInstance" Type="bool">False</Single>
                        <Single Name="Id" Type="long">79</Single>
                      </Single>
                    </List2>
                  </Single>
                  <Single Name="Flags" Type="{668066f2-6069-46b3-8962-8db8d13d7db2}" Method="IArchivable">
                    <Single Name="Flags" Type="int">0</Single>
                    <Single Name="Fixed" Type="bool">False</Single>
                    <Single Name="Extensible" Type="bool">False</Single>
                  </Single>
                  <Null Name="InputFlags" />
                  <List2 Name="InputItems">
                    <Single Type="{acfc6f68-8e3a-4af5-bf81-3dd512095a46}" Method="IArchivable">
                      <Single Name="BoxType" Type="string">LT</Single>
                      <Single Name="Instance" Type="{c9b2f165-48a2-4a45-8326-3952d8a3d708}" Method="IArchivable">
                        <Null Name="Operand" />
                        <Single Name="Type" Type="string"></Single>
                        <Single Name="Comment" Type="string"></Single>
                        <Single Name="SymbolComment" Type="string"></Single>
                        <Single Name="Address" Type="string"></Single>
                        <Single Name="Flags" Type="{668066f2-6069-46b3-8962-8db8d13d7db2}" Method="IArchivable">
                          <Single Name="Flags" Type="int">0</Single>
                          <Single Name="Fixed" Type="bool">False</Single>
                          <Single Name="Extensible" Type="bool">False</Single>
                        </Single>
                        <Single Name="LValue" Type="bool">False</Single>
                        <Single Name="Boolean" Type="bool">False</Single>
                        <Single Name="IsInstance" Type="bool">True</Single>
                        <Single Name="Id" Type="long">80</Single>
                      </Single>
                      <Single Name="OutputItems" Type="{f40d3e09-c02c-4522-a88c-dac23558cfc4}" Method="IArchivable">
                        <List2 Name="OutputItems">
                          <Null />
                        </List2>
                      </Single>
                      <Single Name="Flags" Type="{668066f2-6069-46b3-8962-8db8d13d7db2}" Method="IArchivable">
                        <Single Name="Flags" Type="int">0</Single>
                        <Single Name="Fixed" Type="bool">False</Single>
                        <Single Name="Extensible" Type="bool">False</Single>
                      </Single>
                      <Null Name="InputFlags" />
                      <List2 Name="InputItems">
                        <Single Type="{5f9848d3-568d-4cc5-9e31-8e28e9607ff1}" Method="IArchivable">
                          <Null Name="Input" />
                          <Single Name="Flags" Type="{668066f2-6069-46b3-8962-8db8d13d7db2}" Method="IArchivable">
                            <Single Name="Flags" Type="int">0</Single>
                            <Single Name="Fixed" Type="bool">False</Single>
                            <Single Name="Extensible" Type="bool">False</Single>
                          </Single>
                          <Single Name="Id" Type="long">82</Single>
                        </Single>
                        <Single Type="{9de7f100-1b87-424c-a62e-45b0cfc85ed2}" Method="IArchivable">
                          <Single Name="Operand" Type="{c9b2f165-48a2-4a45-8326-3952d8a3d708}" Method="IArchivable">
                            <Single Name="Operand" Type="string">CV</Single>
                            <Single Name="Type" Type="string">WORD</Single>
                            <Single Name="Comment" Type="string"></Single>
                            <Single Name="SymbolComment" Type="string"></Single>
                            <Single Name="Address" Type="string"></Single>
                            <Single Name="Flags" Type="{668066f2-6069-46b3-8962-8db8d13d7db2}" Method="IArchivable">
                              <Single Name="Flags" Type="int">0</Single>
                              <Single Name="Fixed" Type="bool">False</Single>
                              <Single Name="Extensible" Type="bool">False</Single>
                            </Single>
                            <Single Name="LValue" Type="bool">False</Single>
                            <Single Name="Boolean" Type="bool">False</Single>
                            <Single Name="IsInstance" Type="bool">False</Single>
                            <Single Name="Id" Type="long">84</Single>
                          </Single>
                          <Single Name="Id" Type="long">83</Single>
                        </Single>
                        <Single Type="{9de7f100-1b87-424c-a62e-45b0cfc85ed2}" Method="IArchivable">
                          <Single Name="Operand" Type="{c9b2f165-48a2-4a45-8326-3952d8a3d708}" Method="IArchivable">
                            <Single Name="Operand" Type="string">RV</Single>
                            <Single Name="Type" Type="string">WORD</Single>
                            <Single Name="Comment" Type="string"></Single>
                            <Single Name="SymbolComment" Type="string"></Single>
                            <Single Name="Address" Type="string"></Single>
                            <Single Name="Flags" Type="{668066f2-6069-46b3-8962-8db8d13d7db2}" Method="IArchivable">
                              <Single Name="Flags" Type="int">0</Single>
                              <Single Name="Fixed" Type="bool">False</Single>
                              <Single Name="Extensible" Type="bool">False</Single>
                            </Single>
                            <Single Name="LValue" Type="bool">False</Single>
                            <Single Name="Boolean" Type="bool">False</Single>
                            <Single Name="IsInstance" Type="bool">False</Single>
                            <Single Name="Id" Type="long">86</Single>
                          </Single>
                          <Single Name="Id" Type="long">85</Single>
                        </Single>
                      </List2>
                      <Single Name="InputParam" Type="{71496971-9e0c-4677-a832-b9583b571130}" Method="IArchivable">
                        <List2 Name="Names">
                          <Single Type="string">EN</Single>
                        </List2>
                        <List2 Name="Types">
                          <Single Type="string">BOOL</Single>
                        </List2>
                      </Single>
                      <Single Name="OutputParam" Type="{71496971-9e0c-4677-a832-b9583b571130}" Method="IArchivable">
                        <List2 Name="Names">
                          <Single Type="string"></Single>
                        </List2>
                        <List2 Name="Types">
                          <Single Type="string">BOOL</Single>
                        </List2>
                      </Single>
                      <Single Name="CallType" Type="{bffb3c53-f105-4e85-aba2-e30df579d75f}">Lt</Single>
                      <Single Name="EN" Type="bool">True</Single>
                      <Single Name="ENO" Type="bool">False</Single>
                      <Null Name="STSnippet" />
                      <Single Name="ContainsExtensibleInputs" Type="bool">False</Single>
                      <Single Name="ProvidesSTSnippet" Type="bool">False</Single>
                      <Single Name="Id" Type="long">81</Single>
                    </Single>
                    <Single Type="{9de7f100-1b87-424c-a62e-45b0cfc85ed2}" Method="IArchivable">
                      <Single Name="Operand" Type="{c9b2f165-48a2-4a45-8326-3952d8a3d708}" Method="IArchivable">
                        <Single Name="Operand" Type="string">RV</Single>
                        <Single Name="Type" Type="string">WORD</Single>
                        <Single Name="Comment" Type="string"></Single>
                        <Single Name="SymbolComment" Type="string"></Single>
                        <Single Name="Address" Type="string"></Single>
                        <Single Name="Flags" Type="{668066f2-6069-46b3-8962-8db8d13d7db2}" Method="IArchivable">
                          <Single Name="Flags" Type="int">0</Single>
                          <Single Name="Fixed" Type="bool">False</Single>
                          <Single Name="Extensible" Type="bool">False</Single>
                        </Single>
                        <Single Name="LValue" Type="bool">False</Single>
                        <Single Name="Boolean" Type="bool">False</Single>
                        <Single Name="IsInstance" Type="bool">False</Single>
                        <Single Name="Id" Type="long">88</Single>
                      </Single>
                      <Single Name="Id" Type="long">87</Single>
                    </Single>
                  </List2>
                  <Single Name="InputParam" Type="{71496971-9e0c-4677-a832-b9583b571130}" Method="IArchivable">
                    <List2 Name="Names">
                      <Single Type="string">EN</Single>
                    </List2>
                    <List2 Name="Types">
                      <Single Type="string">BOOL</Single>
                    </List2>
                  </Single>
                  <Single Name="OutputParam" Type="{71496971-9e0c-4677-a832-b9583b571130}" Method="IArchivable">
                    <List2 Name="Names">
                      <Single Type="string">ENO</Single>
                      <Single Type="string"></Single>
                    </List2>
                    <List2 Name="Types">
                      <Single Type="string">BOOL</Single>
                      <Single Type="string"></Single>
                    </List2>
                  </Single>
                  <Single Name="CallType" Type="{bffb3c53-f105-4e85-aba2-e30df579d75f}">Move</Single>
                  <Single Name="EN" Type="bool">True</Single>
                  <Single Name="ENO" Type="bool">True</Single>
                  <Null Name="STSnippet" />
                  <Single Name="ContainsExtensibleInputs" Type="bool">False</Single>
                  <Single Name="ProvidesSTSnippet" Type="bool">False</Single>
                  <Single Name="Id" Type="long">78</Single>
                </Single>
              </List2>
              <List2 Name="Connectors" />
              <Single Name="Id" Type="long">76</Single>
            </Single>
            <Single Type="{d9a99d73-b633-47db-b876-a752acb25871}" Method="IArchivable">
              <Single Name="ILActive" Type="bool">False</Single>
              <Single Name="FBDValid" Type="bool">False</Single>
              <Single Name="ILValid" Type="bool">False</Single>
              <List2 Name="ILLines" />
              <Single Name="Comment" Type="string"></Single>
              <Single Name="Title" Type="string"></Single>
              <Single Name="Label" Type="string"></Single>
              <Single Name="OutCommented" Type="bool">False</Single>
              <List2 Name="NetworkItems">
                <Single Type="{acfc6f68-8e3a-4af5-bf81-3dd512095a46}" Method="IArchivable">
                  <Single Name="BoxType" Type="string">ADD</Single>
                  <Single Name="Instance" Type="{c9b2f165-48a2-4a45-8326-3952d8a3d708}" Method="IArchivable">
                    <Null Name="Operand" />
                    <Single Name="Type" Type="string"></Single>
                    <Single Name="Comment" Type="string"></Single>
                    <Single Name="SymbolComment" Type="string"></Single>
                    <Single Name="Address" Type="string"></Single>
                    <Single Name="Flags" Type="{668066f2-6069-46b3-8962-8db8d13d7db2}" Method="IArchivable">
                      <Single Name="Flags" Type="int">0</Single>
                      <Single Name="Fixed" Type="bool">False</Single>
                      <Single Name="Extensible" Type="bool">False</Single>
                    </Single>
                    <Single Name="LValue" Type="bool">False</Single>
                    <Single Name="Boolean" Type="bool">False</Single>
                    <Single Name="IsInstance" Type="bool">True</Single>
                    <Single Name="Id" Type="long">42</Single>
                  </Single>
                  <Single Name="OutputItems" Type="{f40d3e09-c02c-4522-a88c-dac23558cfc4}" Method="IArchivable">
                    <List2 Name="OutputItems">
                      <Null />
                      <Single Type="{c9b2f165-48a2-4a45-8326-3952d8a3d708}" Method="IArchivable">
                        <Single Name="Operand" Type="string">CV</Single>
                        <Single Name="Type" Type="string">WORD</Single>
                        <Single Name="Comment" Type="string"></Single>
                        <Single Name="SymbolComment" Type="string"></Single>
                        <Single Name="Address" Type="string"></Single>
                        <Single Name="Flags" Type="{668066f2-6069-46b3-8962-8db8d13d7db2}" Method="IArchivable">
                          <Single Name="Flags" Type="int">0</Single>
                          <Single Name="Fixed" Type="bool">False</Single>
                          <Single Name="Extensible" Type="bool">False</Single>
                        </Single>
                        <Single Name="LValue" Type="bool">True</Single>
                        <Single Name="Boolean" Type="bool">False</Single>
                        <Single Name="IsInstance" Type="bool">False</Single>
                        <Single Name="Id" Type="long">44</Single>
                      </Single>
                    </List2>
                  </Single>
                  <Single Name="Flags" Type="{668066f2-6069-46b3-8962-8db8d13d7db2}" Method="IArchivable">
                    <Single Name="Flags" Type="int">0</Single>
                    <Single Name="Fixed" Type="bool">False</Single>
                    <Single Name="Extensible" Type="bool">False</Single>
                  </Single>
                  <Null Name="InputFlags" />
                  <List2 Name="InputItems">
                    <Single Type="{9de7f100-1b87-424c-a62e-45b0cfc85ed2}" Method="IArchivable">
                      <Single Name="Operand" Type="{c9b2f165-48a2-4a45-8326-3952d8a3d708}" Method="IArchivable">
                        <Single Name="Operand" Type="string">CU</Single>
                        <Single Name="Type" Type="string">BOOL</Single>
                        <Single Name="Comment" Type="string"></Single>
                        <Single Name="SymbolComment" Type="string"></Single>
                        <Single Name="Address" Type="string"></Single>
                        <Single Name="Flags" Type="{668066f2-6069-46b3-8962-8db8d13d7db2}" Method="IArchivable">
                          <Single Name="Flags" Type="int">16</Single>
                          <Single Name="Fixed" Type="bool">True</Single>
                          <Single Name="Extensible" Type="bool">False</Single>
                        </Single>
                        <Single Name="LValue" Type="bool">False</Single>
                        <Single Name="Boolean" Type="bool">True</Single>
                        <Single Name="IsInstance" Type="bool">False</Single>
                        <Single Name="Id" Type="long">38</Single>
                      </Single>
                      <Single Name="Id" Type="long">37</Single>
                    </Single>
                    <Single Type="{9de7f100-1b87-424c-a62e-45b0cfc85ed2}" Method="IArchivable">
                      <Single Name="Operand" Type="{c9b2f165-48a2-4a45-8326-3952d8a3d708}" Method="IArchivable">
                        <Single Name="Operand" Type="string">CV</Single>
                        <Single Name="Type" Type="string">WORD</Single>
                        <Single Name="Comment" Type="string"></Single>
                        <Single Name="SymbolComment" Type="string"></Single>
                        <Single Name="Address" Type="string"></Single>
                        <Single Name="Flags" Type="{668066f2-6069-46b3-8962-8db8d13d7db2}" Method="IArchivable">
                          <Single Name="Flags" Type="int">0</Single>
                          <Single Name="Fixed" Type="bool">False</Single>
                          <Single Name="Extensible" Type="bool">False</Single>
                        </Single>
                        <Single Name="LValue" Type="bool">False</Single>
                        <Single Name="Boolean" Type="bool">False</Single>
                        <Single Name="IsInstance" Type="bool">False</Single>
                        <Single Name="Id" Type="long">46</Single>
                      </Single>
                      <Single Name="Id" Type="long">45</Single>
                    </Single>
                    <Single Type="{9de7f100-1b87-424c-a62e-45b0cfc85ed2}" Method="IArchivable">
                      <Single Name="Operand" Type="{c9b2f165-48a2-4a45-8326-3952d8a3d708}" Method="IArchivable">
                        <Single Name="Operand" Type="string">1</Single>
                        <Single Name="Type" Type="string">INT</Single>
                        <Single Name="Comment" Type="string"></Single>
                        <Single Name="SymbolComment" Type="string"></Single>
                        <Single Name="Address" Type="string"></Single>
                        <Single Name="Flags" Type="{668066f2-6069-46b3-8962-8db8d13d7db2}" Method="IArchivable">
                          <Single Name="Flags" Type="int">0</Single>
                          <Single Name="Fixed" Type="bool">False</Single>
                          <Single Name="Extensible" Type="bool">False</Single>
                        </Single>
                        <Single Name="LValue" Type="bool">False</Single>
                        <Single Name="Boolean" Type="bool">False</Single>
                        <Single Name="IsInstance" Type="bool">False</Single>
                        <Single Name="Id" Type="long">48</Single>
                      </Single>
                      <Single Name="Id" Type="long">47</Single>
                    </Single>
                  </List2>
                  <Single Name="InputParam" Type="{71496971-9e0c-4677-a832-b9583b571130}" Method="IArchivable">
                    <List2 Name="Names">
                      <Single Type="string">EN</Single>
                    </List2>
                    <List2 Name="Types">
                      <Single Type="string">BOOL</Single>
                    </List2>
                  </Single>
                  <Single Name="OutputParam" Type="{71496971-9e0c-4677-a832-b9583b571130}" Method="IArchivable">
                    <List2 Name="Names">
                      <Single Type="string">ENO</Single>
                      <Single Type="string"></Single>
                    </List2>
                    <List2 Name="Types">
                      <Single Type="string">BOOL</Single>
                      <Single Type="string">INT</Single>
                    </List2>
                  </Single>
                  <Single Name="CallType" Type="{bffb3c53-f105-4e85-aba2-e30df579d75f}">Add</Single>
                  <Single Name="EN" Type="bool">True</Single>
                  <Single Name="ENO" Type="bool">True</Single>
                  <Null Name="STSnippet" />
                  <Single Name="ContainsExtensibleInputs" Type="bool">False</Single>
                  <Single Name="ProvidesSTSnippet" Type="bool">False</Single>
                  <Single Name="Id" Type="long">43</Single>
                </Single>
              </List2>
              <List2 Name="Connectors" />
              <Single Name="Id" Type="long">36</Single>
            </Single>
            <Single Type="{d9a99d73-b633-47db-b876-a752acb25871}" Method="IArchivable">
              <Single Name="ILActive" Type="bool">False</Single>
              <Single Name="FBDValid" Type="bool">False</Single>
              <Single Name="ILValid" Type="bool">False</Single>
              <List2 Name="ILLines" />
              <Single Name="Comment" Type="string"></Single>
              <Single Name="Title" Type="string"></Single>
              <Single Name="Label" Type="string"></Single>
              <Single Name="OutCommented" Type="bool">False</Single>
              <List2 Name="NetworkItems">
                <Single Type="{9873c309-1f09-4ebf-9078-42d8057ef11b}" Method="IArchivable">
                  <Single Name="OutputItems" Type="{f40d3e09-c02c-4522-a88c-dac23558cfc4}" Method="IArchivable">
                    <List2 Name="OutputItems">
                      <Single Type="{c9b2f165-48a2-4a45-8326-3952d8a3d708}" Method="IArchivable">
                        <Single Name="Operand" Type="string">Q</Single>
                        <Single Name="Type" Type="string">BOOL</Single>
                        <Single Name="Comment" Type="string"></Single>
                        <Single Name="SymbolComment" Type="string"></Single>
                        <Single Name="Address" Type="string"></Single>
                        <Single Name="Flags" Type="{668066f2-6069-46b3-8962-8db8d13d7db2}" Method="IArchivable">
                          <Single Name="Flags" Type="int">0</Single>
                          <Single Name="Fixed" Type="bool">False</Single>
                          <Single Name="Extensible" Type="bool">False</Single>
                        </Single>
                        <Single Name="LValue" Type="bool">True</Single>
                        <Single Name="Boolean" Type="bool">True</Single>
                        <Single Name="IsInstance" Type="bool">False</Single>
                        <Single Name="Id" Type="long">59</Single>
                      </Single>
                    </List2>
                  </Single>
                  <Single Name="Flags" Type="{668066f2-6069-46b3-8962-8db8d13d7db2}" Method="IArchivable">
                    <Single Name="Flags" Type="int">0</Single>
                    <Single Name="Fixed" Type="bool">False</Single>
                    <Single Name="Extensible" Type="bool">False</Single>
                  </Single>
                  <Single Name="RValue" Type="{acfc6f68-8e3a-4af5-bf81-3dd512095a46}" Method="IArchivable">
                    <Single Name="BoxType" Type="string">GE</Single>
                    <Single Name="Instance" Type="{c9b2f165-48a2-4a45-8326-3952d8a3d708}" Method="IArchivable">
                      <Null Name="Operand" />
                      <Single Name="Type" Type="string"></Single>
                      <Single Name="Comment" Type="string"></Single>
                      <Single Name="SymbolComment" Type="string"></Single>
                      <Single Name="Address" Type="string"></Single>
                      <Single Name="Flags" Type="{668066f2-6069-46b3-8962-8db8d13d7db2}" Method="IArchivable">
                        <Single Name="Flags" Type="int">0</Single>
                        <Single Name="Fixed" Type="bool">False</Single>
                        <Single Name="Extensible" Type="bool">False</Single>
                      </Single>
                      <Single Name="LValue" Type="bool">False</Single>
                      <Single Name="Boolean" Type="bool">False</Single>
                      <Single Name="IsInstance" Type="bool">True</Single>
                      <Single Name="Id" Type="long">50</Single>
                    </Single>
                    <Single Name="OutputItems" Type="{f40d3e09-c02c-4522-a88c-dac23558cfc4}" Method="IArchivable">
                      <List2 Name="OutputItems">
                        <Null />
                      </List2>
                    </Single>
                    <Single Name="Flags" Type="{668066f2-6069-46b3-8962-8db8d13d7db2}" Method="IArchivable">
                      <Single Name="Flags" Type="int">0</Single>
                      <Single Name="Fixed" Type="bool">False</Single>
                      <Single Name="Extensible" Type="bool">False</Single>
                    </Single>
                    <Null Name="InputFlags" />
                    <List2 Name="InputItems">
                      <Single Type="{5f9848d3-568d-4cc5-9e31-8e28e9607ff1}" Method="IArchivable">
                        <Null Name="Input" />
                        <Single Name="Flags" Type="{668066f2-6069-46b3-8962-8db8d13d7db2}" Method="IArchivable">
                          <Single Name="Flags" Type="int">0</Single>
                          <Single Name="Fixed" Type="bool">False</Single>
                          <Single Name="Extensible" Type="bool">False</Single>
                        </Single>
                        <Single Name="Id" Type="long">58</Single>
                      </Single>
                      <Single Type="{9de7f100-1b87-424c-a62e-45b0cfc85ed2}" Method="IArchivable">
                        <Single Name="Operand" Type="{c9b2f165-48a2-4a45-8326-3952d8a3d708}" Method="IArchivable">
                          <Single Name="Operand" Type="string">CV</Single>
                          <Single Name="Type" Type="string">WORD</Single>
                          <Single Name="Comment" Type="string"></Single>
                          <Single Name="SymbolComment" Type="string"></Single>
                          <Single Name="Address" Type="string"></Single>
                          <Single Name="Flags" Type="{668066f2-6069-46b3-8962-8db8d13d7db2}" Method="IArchivable">
                            <Single Name="Flags" Type="int">0</Single>
                            <Single Name="Fixed" Type="bool">False</Single>
                            <Single Name="Extensible" Type="bool">False</Single>
                          </Single>
                          <Single Name="LValue" Type="bool">False</Single>
                          <Single Name="Boolean" Type="bool">False</Single>
                          <Single Name="IsInstance" Type="bool">False</Single>
                          <Single Name="Id" Type="long">55</Single>
                        </Single>
                        <Single Name="Id" Type="long">54</Single>
                      </Single>
                      <Single Type="{9de7f100-1b87-424c-a62e-45b0cfc85ed2}" Method="IArchivable">
                        <Single Name="Operand" Type="{c9b2f165-48a2-4a45-8326-3952d8a3d708}" Method="IArchivable">
                          <Single Name="Operand" Type="string">PV</Single>
                          <Single Name="Type" Type="string">WORD</Single>
                          <Single Name="Comment" Type="string"></Single>
                          <Single Name="SymbolComment" Type="string"></Single>
                          <Single Name="Address" Type="string"></Single>
                          <Single Name="Flags" Type="{668066f2-6069-46b3-8962-8db8d13d7db2}" Method="IArchivable">
                            <Single Name="Flags" Type="int">0</Single>
                            <Single Name="Fixed" Type="bool">False</Single>
                            <Single Name="Extensible" Type="bool">False</Single>
                          </Single>
                          <Single Name="LValue" Type="bool">False</Single>
                          <Single Name="Boolean" Type="bool">False</Single>
                          <Single Name="IsInstance" Type="bool">False</Single>
                          <Single Name="Id" Type="long">57</Single>
                        </Single>
                        <Single Name="Id" Type="long">56</Single>
                      </Single>
                    </List2>
                    <Single Name="InputParam" Type="{71496971-9e0c-4677-a832-b9583b571130}" Method="IArchivable">
                      <List2 Name="Names">
                        <Single Type="string">EN</Single>
                      </List2>
                      <List2 Name="Types">
                        <Single Type="string">BOOL</Single>
                      </List2>
                    </Single>
                    <Single Name="OutputParam" Type="{71496971-9e0c-4677-a832-b9583b571130}" Method="IArchivable">
                      <List2 Name="Names">
                        <Single Type="string"></Single>
                      </List2>
                      <List2 Name="Types">
                        <Single Type="string">BOOL</Single>
                      </List2>
                    </Single>
                    <Single Name="CallType" Type="{bffb3c53-f105-4e85-aba2-e30df579d75f}">Ge</Single>
                    <Single Name="EN" Type="bool">True</Single>
                    <Single Name="ENO" Type="bool">False</Single>
                    <Null Name="STSnippet" />
                    <Single Name="ContainsExtensibleInputs" Type="bool">False</Single>
                    <Single Name="ProvidesSTSnippet" Type="bool">False</Single>
                    <Single Name="Id" Type="long">51</Single>
                  </Single>
                  <Single Name="Id" Type="long">60</Single>
                </Single>
              </List2>
              <List2 Name="Connectors" />
              <Single Name="Id" Type="long">49</Single>
            </Single>
          </List2>
          <Single Name="BranchCounter" Type="int">0</Single>
          <Single Name="ValidIds" Type="bool">True</Single>
        </Single>
        <Single Name="Interface" Type="{a9ed5b7e-75c5-4651-af16-d2c27e98cb94}" Method="IArchivable">
          <Single Name="TextDocument" Type="{f3878285-8e4f-490b-bb1b-9acbb7eb04db}" Method="IArchivable">
            <Array Name="TextLines" Type="{a5de0b0b-1cb5-4913-ac21-9d70293ec00d}">
              <Single Type="{a5de0b0b-1cb5-4913-ac21-9d70293ec00d}" Method="IArchivable">
                <Single Name="Id" Type="long">89</Single>
                <Null Name="Tag" />
                <Single Name="Text" Type="string">FUNCTION_BLOCK RCTU // Rententive up counter</Single>
              </Single>
              <Single Type="{a5de0b0b-1cb5-4913-ac21-9d70293ec00d}" Method="IArchivable">
                <Single Name="Id" Type="long">90</Single>
                <Null Name="Tag" />
                <Single Name="Text" Type="string">VAR_INPUT</Single>
              </Single>
              <Single Type="{a5de0b0b-1cb5-4913-ac21-9d70293ec00d}" Method="IArchivable">
                <Single Name="Id" Type="long">91</Single>
                <Null Name="Tag" />
                <Single Name="Text" Type="string">	CU: BOOL; // Count Up</Single>
              </Single>
              <Single Type="{a5de0b0b-1cb5-4913-ac21-9d70293ec00d}" Method="IArchivable">
                <Single Name="Id" Type="long">92</Single>
                <Null Name="Tag" />
                <Single Name="Text" Type="string">	RESET: BOOL; // Reset Counter to 0</Single>
              </Single>
              <Single Type="{a5de0b0b-1cb5-4913-ac21-9d70293ec00d}" Method="IArchivable">
                <Single Name="Id" Type="long">93</Single>
                <Null Name="Tag" />
                <Single Name="Text" Type="string">	PV: WORD; // Counter Limit</Single>
              </Single>
              <Single Type="{a5de0b0b-1cb5-4913-ac21-9d70293ec00d}" Method="IArchivable">
                <Single Name="Id" Type="long">94</Single>
                <Null Name="Tag" />
                <Single Name="Text" Type="string">	RV: WORD; // Starting Value</Single>
              </Single>
              <Single Type="{a5de0b0b-1cb5-4913-ac21-9d70293ec00d}" Method="IArchivable">
                <Single Name="Id" Type="long">95</Single>
                <Null Name="Tag" />
                <Single Name="Text" Type="string">END_VAR</Single>
              </Single>
              <Single Type="{a5de0b0b-1cb5-4913-ac21-9d70293ec00d}" Method="IArchivable">
                <Single Name="Id" Type="long">96</Single>
                <Null Name="Tag" />
                <Single Name="Text" Type="string">VAR_OUTPUT</Single>
              </Single>
              <Single Type="{a5de0b0b-1cb5-4913-ac21-9d70293ec00d}" Method="IArchivable">
                <Single Name="Id" Type="long">97</Single>
                <Null Name="Tag" />
                <Single Name="Text" Type="string">	Q: BOOL; // Counter reached the Limit</Single>
              </Single>
              <Single Type="{a5de0b0b-1cb5-4913-ac21-9d70293ec00d}" Method="IArchivable">
                <Single Name="Id" Type="long">98</Single>
                <Null Name="Tag" />
                <Single Name="Text" Type="string">	CV: WORD; // Current Counter Value</Single>
              </Single>
              <Single Type="{a5de0b0b-1cb5-4913-ac21-9d70293ec00d}" Method="IArchivable">
                <Single Name="Id" Type="long">99</Single>
                <Null Name="Tag" />
                <Single Name="Text" Type="string">END_VAR</Single>
              </Single>
              <Single Type="{a5de0b0b-1cb5-4913-ac21-9d70293ec00d}" Method="IArchivable">
                <Single Name="Id" Type="long">100</Single>
                <Null Name="Tag" />
                <Single Name="Text" Type="string">VAR</Single>
              </Single>
              <Single Type="{a5de0b0b-1cb5-4913-ac21-9d70293ec00d}" Method="IArchivable">
                <Single Name="Id" Type="long">102</Single>
                <Null Name="Tag" />
                <Single Name="Text" Type="string">END_VAR</Single>
              </Single>
              <Single Type="{a5de0b0b-1cb5-4913-ac21-9d70293ec00d}" Method="IArchivable">
                <Single Name="Id" Type="long">1</Single>
                <Null Name="Tag" />
                <Single Name="Text" Type="string"></Single>
              </Single>
            </Array>
          </Single>
        </Single>
        <Single Name="UniqueIdGenerator" Type="string">102</Single>
        <Single Name="POULevel" Type="{8e575c5b-1d37-49c6-941b-5c0ec7874787}">Standard</Single>
        <List Name="ChildObjectGuids" Type="System.Collections.ArrayList" />
        <Single Name="AddAttributeSubsequent" Type="bool">False</Single>
      </Single>
      <Single Name="ParentSVNodeGuid" Type="System.Guid">9b280665-8d53-4807-82ac-923441df304e</Single>
      <Array Name="Path" Type="string">
        <Single Type="string">Device</Single>
        <Single Type="string">PLC Logic</Single>
        <Single Type="string">Application</Single>
      </Array>
      <Single Name="Index" Type="int">-1</Single>
    </Single>
  </List2>
  <Null Name="ProfileName" />
</Single>  </StructuredView>
</ExportFile>
